{
  "note": "Unified job-free DCL sentinel v3. It extends the exact v2 settings with the live-proven Approach movement transaction and explicit first-owner-wins arbitration over the shared synthetic Reaction pass-2 queue. The ids and reach are bounded technical fixtures, not production job or balance policy.",
  "inputs": [
    "work/1784397292-battle-runtime-settings.dcl-unified-sentinel-v2.json",
    "work/1784398672-battle-runtime-settings.dcl-approach-integration-fragment.json"
  ],
  "resolutions": {},
  "patch": {},
  "output": "work/1784398672-battle-runtime-settings.dcl-unified-sentinel-v3.json"
}
